MANIFEST.in
README.md
requirements.txt
setup.cfg
setup.py
versioneer.py
botcity/plugins/csv/__init__.py
botcity/plugins/csv/_version.py
botcity/plugins/csv/plugin.py
botcity/plugins/csv/tests/test_import.py
botcity/plugins/csv/tests/test_plugin.py
botcity_csv_plugin.egg-info/PKG-INFO
botcity_csv_plugin.egg-info/SOURCES.txt
botcity_csv_plugin.egg-info/dependency_links.txt
botcity_csv_plugin.egg-info/requires.txt
botcity_csv_plugin.egg-info/top_level.txt
tests/test_import.py
tests/test_plugin.py