Metadata-Version: 2.2
Name: botcity-csv-plugin
Version: 0.2.2
Home-page: https://bitbucket.org/botcitydev/bot-csv-plugin-python.git
Requires-Python: >=3.7
Requires-Dist: pandas
Requires-Dist: numpy
Dynamic: description
Dynamic: description-content-type
Dynamic: home-page
Dynamic: requires-dist
Dynamic: requires-python
